date_fuzz/__init__.py
date_fuzz/extraction.py
date_fuzz/extraction_classes.py
date_fuzz-0.0.8.dist-info/METADATA
date_fuzz-0.0.8.dist-info/WHEEL
date_fuzz-0.0.8.dist-info/licenses/LICENSE
date_fuzz-0.0.8.dist-info/RECORD
