Metadata-Version: 2.4
Name: date-fuzz
Version: 0.0.8
Summary: A Python module to fuzzy extract dates from text corpuses.
Project-URL: Homepage, https://hal609.github.io/date-fuzz/
Project-URL: Repository, https://github.com/hal609/date-fuzz
Project-URL: Documentation, https://hal609.github.io/date-fuzz/
Author-email: Hal Kolb <hal@kolb.co.uk>
License-File: LICENSE
Keywords: python
Classifier: Intended Audience :: Developers
Classifier: Programming Language :: Python
Classifier: Programming Language :: Python :: 3
Classifier: Programming Language :: Python :: 3.10
Classifier: Programming Language :: Python :: 3.11
Classifier: Programming Language :: Python :: 3.12
Classifier: Programming Language :: Python :: 3.13
Classifier: Programming Language :: Python :: 3.14
Classifier: Topic :: Software Development :: Libraries :: Python Modules
Requires-Python: <4.0,>=3.10
